/*
 * The Apache Software License, Version 1.1
 *
 * Copyright (c) 2002 The Apache Software Foundation.  All rights
 * reserved.
 *
 * Redistribution and use in source and binary forms, with or without
 * modification, are permitted provided that the following conditions
 * are met:
 *
 * 1. Redistributions of source code must retain the above copyright
 *    notice, this list of conditions and the following disclaimer.
 *
 * 2. Redistributions in binary form must reproduce the above copyright
 *    notice, this list of conditions and the following disclaimer in
 *    the documentation and/or other materials provided with the
 *    distribution.
 *
 * 3. The end-user documentation included with the redistribution,
 *    if any, must include the following acknowledgment:
 *       "This product includes software developed by the
 *        Apache Software Foundation (http://www.apache.org/)."
 *    Alternately, this acknowledgment may appear in the software itself,
 *    if and wherever such third-party acknowledgments normally appear.
 *
 * 4. The names "Apache" and "Apache Software Foundation" must
 *    not be used to endorse or promote products derived from this
 *    software without prior written permission. For written
 *    permission, please contact apache@apache.org.
 *
 * 5. Products derived from this software may not be called "Apache",
 *    nor may "Apache" appear in their name, without prior written
 *    permission of the Apache Software Foundation.
 *
 * THIS SOFTWARE IS PROVIDED ``AS IS'' AND ANY EXPRESSED OR IMPLIED
 * WARRANTIES, INCLUDING, BUT NOT LIMITED TO, THE IMPLIED WARRANTIES
 * OF MERCHANTABILITY AND FITNESS FOR A PARTICULAR PURPOSE ARE
 * DISCLAIMED.  IN NO EVENT SHALL THE APACHE SOFTWARE FOUNDATION OR
 * ITS CONTRIBUTORS BE LIABLE FOR ANY DIRECT, INDIRECT, INCIDENTAL,
 * SPECIAL, EXEMPLARY, OR CONSEQUENTIAL DAMAGES (INCLUDING, BUT NOT
 * LIMITED TO, PROCUREMENT OF SUBSTITUTE GOODS OR SERVICES; LOSS OF
 * USE, DATA, OR PROFITS; OR BUSINESS INTERRUPTION) HOWEVER CAUSED AND
 * ON ANY THEORY OF LIABILITY, WHETHER IN CONTRACT, STRICT LIABILITY,
 * OR TORT (INCLUDING NEGLIGENCE OR OTHERWISE) ARISING IN ANY WAY OUT
 * OF THE USE OF THIS SOFTWARE, EVEN IF ADVISED OF THE POSSIBILITY OF
 * SUCH DAMAGE.
 * ====================================================================
 *
 * This software consists of voluntary contributions made by many
 * individuals on behalf of the Apache Software Foundation.  For more
 * information on the Apache Software Foundation, please see
 * <http://www.apache.org/>.
 */
package net.sf.cglib.core;

public class Opcodes
{
    private Opcodes() { }

    private static final int NEWARRAY_BOOLEAN = 4;
    private static final int NEWARRAY_CHAR = 5;
    private static final int NEWARRAY_FLOAT = 6;
    private static final int NEWARRAY_DOUBLE = 7;
    private static final int NEWARRAY_BYTE = 8;
    private static final int NEWARRAY_SHORT = 9;
    private static final int NEWARRAY_INT = 10;
    private static final int NEWARRAY_LONG = 11;

    public static int newarray(Class clazz) {
        switch (clazz.getName().charAt(0)) {
        case 'B': return NEWARRAY_BYTE;
        case 'C': return NEWARRAY_CHAR;
        case 'D': return NEWARRAY_DOUBLE;
        case 'F': return NEWARRAY_FLOAT;
        case 'I': return NEWARRAY_INT;
        case 'J': return NEWARRAY_LONG;
        case 'S': return NEWARRAY_SHORT;
        case 'Z': return NEWARRAY_BOOLEAN;
        }
        return -1; // error
    }
    
    public static int iconst(int value) {
        switch (value) {
        case -1: return ICONST_M1;
        case 0: return ICONST_0;
        case 1: return ICONST_1;
        case 2: return ICONST_2;
        case 3: return ICONST_3;
        case 4: return ICONST_4;
        case 5: return ICONST_5;
        }
        return -1; // error
    }

    public static int lconst(long value) {
        if (value == 0L) {
            return LCONST_0;
        } else if (value == 1L) {
            return LCONST_1;
        } else {
            return -1; // error
        }
    }

    public static int fconst(float value) {
        if (value == 0f) {
            return FCONST_0;
        } else if (value == 1f) {
            return FCONST_1;
        } else if (value == 2f) {
            return FCONST_2;
        } else {
            return -1; // error
        }
    }

    public static int dconst(double value) {
        if (value == 0d) {
            return DCONST_0;
        } else if (value == 1d) {
            return DCONST_1;
        } else {
            return -1; // error
        }
    }

    public static final int NOP = 0;
    public static final int ACONST_NULL = 1;
    public static final int ICONST_M1 = 2;
    public static final int ICONST_0 = 3;
    public static final int ICONST_1 = 4;
    public static final int ICONST_2 = 5;
    public static final int ICONST_3 = 6;
    public static final int ICONST_4 = 7;
    public static final int ICONST_5 = 8;
    public static final int LCONST_0 = 9;
    public static final int LCONST_1 = 10;
    public static final int FCONST_0 = 11;
    public static final int FCONST_1 = 12;
    public static final int FCONST_2 = 13;
    public static final int DCONST_0 = 14;
    public static final int DCONST_1 = 15;
    public static final int BIPUSH = 16;
    public static final int SIPUSH = 17;
    public static final int LDC = 18;
    public static final int LDC_W = 19;
    public static final int LDC2_W = 20;
    public static final int ILOAD = 21;
    public static final int LLOAD = 22;
    public static final int FLOAD = 23;
    public static final int DLOAD = 24;
    public static final int ALOAD = 25;
    public static final int ILOAD_0 = 26;
    public static final int ILOAD_1 = 27;
    public static final int ILOAD_2 = 28;
    public static final int ILOAD_3 = 29;
    public static final int LLOAD_0 = 30;
    public static final int LLOAD_1 = 31;
    public static final int LLOAD_2 = 32;
    public static final int LLOAD_3 = 33;
    public static final int FLOAD_0 = 34;
    public static final int FLOAD_1 = 35;
    public static final int FLOAD_2 = 36;
    public static final int FLOAD_3 = 37;
    public static final int DLOAD_0 = 38;
    public static final int DLOAD_1 = 39;
    public static final int DLOAD_2 = 40;
    public static final int DLOAD_3 = 41;
    public static final int ALOAD_0 = 42;
    public static final int ALOAD_1 = 43;
    public static final int ALOAD_2 = 44;
    public static final int ALOAD_3 = 45;
    public static final int IALOAD = 46;
    public static final int LALOAD = 47;
    public static final int FALOAD = 48;
    public static final int DALOAD = 49;
    public static final int AALOAD = 50;
    public static final int BALOAD = 51;
    public static final int CALOAD = 52;
    public static final int SALOAD = 53;
    public static final int ISTORE = 54;
    public static final int LSTORE = 55;
    public static final int FSTORE = 56;
    public static final int DSTORE = 57;
    public static final int ASTORE = 58;
    public static final int ISTORE_0 = 59;
    public static final int ISTORE_1 = 60;
    public static final int ISTORE_2 = 61;
    public static final int ISTORE_3 = 62;
    public static final int LSTORE_0 = 63;
    public static final int LSTORE_1 = 64;
    public static final int LSTORE_2 = 65;
    public static final int LSTORE_3 = 66;
    public static final int FSTORE_0 = 67;
    public static final int FSTORE_1 = 68;
    public static final int FSTORE_2 = 69;
    public static final int FSTORE_3 = 70;
    public static final int DSTORE_0 = 71;
    public static final int DSTORE_1 = 72;
    public static final int DSTORE_2 = 73;
    public static final int DSTORE_3 = 74;
    public static final int ASTORE_0 = 75;
    public static final int ASTORE_1 = 76;
    public static final int ASTORE_2 = 77;
    public static final int ASTORE_3 = 78;
    public static final int IASTORE = 79;
    public static final int LASTORE = 80;
    public static final int FASTORE = 81;
    public static final int DASTORE = 82;
    public static final int AASTORE = 83;
    public static final int BASTORE = 84;
    public static final int CASTORE = 85;
    public static final int SASTORE = 86;
    public static final int POP = 87;
    public static final int POP2 = 88;
    public static final int DUP = 89;
    public static final int DUP_X1 = 90;
    public static final int DUP_X2 = 91;
    public static final int DUP2 = 92;
    public static final int DUP2_X1 = 93;
    public static final int DUP2_X2 = 94;
    public static final int SWAP = 95;
    public static final int IADD = 96;
    public static final int LADD = 97;
    public static final int FADD = 98;
    public static final int DADD = 99;
    public static final int ISUB = 100;
    public static final int LSUB = 101;
    public static final int FSUB = 102;
    public static final int DSUB = 103;
    public static final int IMUL = 104;
    public static final int LMUL = 105;
    public static final int FMUL = 106;
    public static final int DMUL = 107;
    public static final int IDIV = 108;
    public static final int LDIV = 109;
    public static final int FDIV = 110;
    public static final int DDIV = 111;
    public static final int IREM = 112;
    public static final int LREM = 113;
    public static final int FREM = 114;
    public static final int DREM = 115;
    public static final int INEG = 116;
    public static final int LNEG = 117;
    public static final int FNEG = 118;
    public static final int DNEG = 119;
    public static final int ISHL = 120;
    public static final int LSHL = 121;
    public static final int ISHR = 122;
    public static final int LSHR = 123;
    public static final int IUSHR = 124;
    public static final int LUSHR = 125;
    public static final int IAND = 126;
    public static final int LAND = 127;
    public static final int IOR = 128;
    public static final int LOR = 129;
    public static final int IXOR = 130;
    public static final int LXOR = 131;
    public static final int IINC = 132;
    public static final int I2L = 133;
    public static final int I2F = 134;
    public static final int I2D = 135;
    public static final int L2I = 136;
    public static final int L2F = 137;
    public static final int L2D = 138;
    public static final int F2I = 139;
    public static final int F2L = 140;
    public static final int F2D = 141;
    public static final int D2I = 142;
    public static final int D2L = 143;
    public static final int D2F = 144;
    public static final int I2B = 145;
    public static final int I2C = 146;
    public static final int I2S = 147;
    public static final int LCMP = 148;
    public static final int FCMPL = 149;
    public static final int FCMPG = 150;
    public static final int DCMPL = 151;
    public static final int DCMPG = 152;
    public static final int IFEQ = 153;
    public static final int IFNE = 154;
    public static final int IFLT = 155;
    public static final int IFGE = 156;
    public static final int IFGT = 157;
    public static final int IFLE = 158;
    public static final int IF_ICMPEQ = 159;
    public static final int IF_ICMPNE = 160;
    public static final int IF_ICMPLT = 161;
    public static final int IF_ICMPGE = 162;
    public static final int IF_ICMPGT = 163;
    public static final int IF_ICMPLE = 164;
    public static final int IF_ACMPEQ = 165;
    public static final int IF_ACMPNE = 166;
    public static final int GOTO = 167;
    public static final int JSR = 168;
    public static final int RET = 169;
    public static final int TABLESWITCH = 170;
    public static final int LOOKUPSWITCH = 171;
    public static final int IRETURN = 172;
    public static final int LRETURN = 173;
    public static final int FRETURN = 174;
    public static final int DRETURN = 175;
    public static final int ARETURN = 176;
    public static final int RETURN = 177;
    public static final int GETSTATIC = 178;
    public static final int PUTSTATIC = 179;
    public static final int GETFIELD = 180;
    public static final int PUTFIELD = 181;
    public static final int INVOKEVIRTUAL = 182;
    public static final int INVOKESPECIAL = 183;
    public static final int INVOKESTATIC = 184;
    public static final int INVOKEINTERFACE = 185;
    public static final int UNUSED = 186;
    public static final int NEW = 187;
    public static final int NEWARRAY = 188;
    public static final int ANEWARRAY = 189;
    public static final int ARRAYLENGTH = 190;
    public static final int ATHROW = 191;           
    public static final int CHECKCAST = 192;
    public static final int INSTANCEOF = 193;
    public static final int MONITORENTER = 194;
    public static final int MONITOREXIT = 195;
    public static final int WIDE = 196;
    public static final int MULTIANEWARRAY = 197;
    public static final int IFNULL = 198;
    public static final int IFNONNULL = 199;
    public static final int GOTO_W = 200;
    public static final int JSR_W = 201;
}
